transcoding/__init__.py
transcoding/__main__.py
transcoding/core.py
transcoding/pattern.py
transcoding/trigger.py
transcoding/transcodings/__init__.py
transcoding/transcodings/csv.py
transcoding/transcodings/inp.py
transcoding-0.2.0.dist-info/LICENSE.rst
transcoding-0.2.0.dist-info/METADATA
transcoding-0.2.0.dist-info/WHEEL
transcoding-0.2.0.dist-info/top_level.txt
transcoding-0.2.0.dist-info/RECORD
