Metadata-Version: 2.1
Name: transcoding
Version: 0.2.0
Summary: Bijective transoding engine for standardized file in- and outputs
Home-page: https://gitlab.mpcdf.mpg.de/dboe/transcoding
Author: Daniel Böckenhoff
Author-email: dboe@ipp.mpg.de
License: MIT License
Project-URL: Documentation, https://transcoding.readthedocs.io
Project-URL: Source, https://gitlab.mpcdf.mpg.de/dboe/transcoding
Keywords: file input output transcoding standardization
Platform: UNKNOWN
Classifier: Development Status :: 3 - Alpha
Classifier: License :: OSI Approved :: MIT License
Classifier: Programming Language :: Python
Classifier: Programming Language :: Python :: 3
Classifier: Programming Language :: Python :: 3.5
Classifier: Programming Language :: Python :: 3.6
Classifier: Programming Language :: Python :: 3.7
Classifier: Programming Language :: Python :: 3.8
Requires-Python: >=3.0
Requires-Dist: pathlib
Requires-Dist: parse
Requires-Dist: more-itertools
Provides-Extra: all
Requires-Dist: sphinx (>=2.2.0) ; extra == 'all'
Requires-Dist: sphinx-rtd-theme (>=0.4.3) ; extra == 'all'
Requires-Dist: flake8 ; extra == 'all'
Requires-Dist: pylint ; extra == 'all'
Requires-Dist: pytest ; extra == 'all'
Requires-Dist: pytest-cov ; extra == 'all'
Requires-Dist: coverage ; extra == 'all'
Requires-Dist: pytest-shutil ; extra == 'all'
Requires-Dist: pytest-virtualenv ; extra == 'all'
Requires-Dist: pytest-fixture-config ; extra == 'all'
Requires-Dist: pytest-xdist ; extra == 'all'
Requires-Dist: bumpversion ; extra == 'all'
Requires-Dist: twine ; extra == 'all'
Requires-Dist: sphinx ; extra == 'all'
Requires-Dist: pre-commit ; extra == 'all'
Requires-Dist: pre-commit-hooks ; extra == 'all'
Requires-Dist: cookiecutter-project-upgrader ; extra == 'all'
Provides-Extra: dev
Requires-Dist: sphinx (>=2.2.0) ; extra == 'dev'
Requires-Dist: sphinx-rtd-theme (>=0.4.3) ; extra == 'dev'
Requires-Dist: flake8 ; extra == 'dev'
Requires-Dist: pylint ; extra == 'dev'
Requires-Dist: pytest ; extra == 'dev'
Requires-Dist: pytest-cov ; extra == 'dev'
Requires-Dist: coverage ; extra == 'dev'
Requires-Dist: pytest-shutil ; extra == 'dev'
Requires-Dist: pytest-virtualenv ; extra == 'dev'
Requires-Dist: pytest-fixture-config ; extra == 'dev'
Requires-Dist: pytest-xdist ; extra == 'dev'
Requires-Dist: bumpversion ; extra == 'dev'
Requires-Dist: twine ; extra == 'dev'
Requires-Dist: sphinx ; extra == 'dev'
Requires-Dist: pre-commit ; extra == 'dev'
Requires-Dist: pre-commit-hooks ; extra == 'dev'
Requires-Dist: cookiecutter-project-upgrader ; extra == 'dev'
Provides-Extra: docs
Requires-Dist: sphinx (>=2.2.0) ; extra == 'docs'
Requires-Dist: sphinx-rtd-theme (>=0.4.3) ; extra == 'docs'
Provides-Extra: tar
Requires-Dist: tarfile ; extra == 'tar'
Provides-Extra: test
Requires-Dist: flake8 ; extra == 'test'
Requires-Dist: pylint ; extra == 'test'
Requires-Dist: pytest ; extra == 'test'
Requires-Dist: pytest-cov ; extra == 'test'
Requires-Dist: coverage ; extra == 'test'
Requires-Dist: pytest-shutil ; extra == 'test'
Requires-Dist: pytest-virtualenv ; extra == 'test'
Requires-Dist: pytest-fixture-config ; extra == 'test'
Requires-Dist: pytest-xdist ; extra == 'test'
